pantsonfire/__init__.py
pantsonfire/cli.py
pantsonfire/config.py
pantsonfire/core.py
pantsonfire/factory.py
pantsonfire/llm.py
pantsonfire/models.py
pantsonfire/extractors/__init__.py
pantsonfire/extractors/base.py
pantsonfire/extractors/external.py
pantsonfire/extractors/internal.py
pantsonfire/extractors/web_scraper.py
pantsonfire/storage/__init__.py
pantsonfire/storage/base.py
pantsonfire/storage/json_storage.py
pantsonfire/storage/oxen_storage.py
pantsonfire-0.1.2.dist-info/licenses/LICENSE
pantsonfire-0.1.2.dist-info/METADATA
pantsonfire-0.1.2.dist-info/WHEEL
pantsonfire-0.1.2.dist-info/entry_points.txt
pantsonfire-0.1.2.dist-info/top_level.txt
pantsonfire-0.1.2.dist-info/RECORD
