Metadata-Version: 2.4
Name: pantsonfire
Version: 0.1.2
Summary: Find wrong information in technical docs online
Home-page: https://github.com/seanmcdonald/pantsonfire
Author: Sean McDonald
Author-email: 
Project-URL: Bug Reports, https://github.com/seanmcdonald/pantsonfire/issues
Project-URL: Source, https://github.com/seanmcdonald/pantsonfire
Project-URL: Documentation, https://github.com/seanmcdonald/pantsonfire#readme
Keywords: documentation,verification,fact-checking,technical-docs,ai,llm,web-scraping
Classifier: Development Status :: 3 - Alpha
Classifier: Intended Audience :: Developers
Classifier: Intended Audience :: Information Technology
Classifier: License :: OSI Approved :: MIT License
Classifier: Operating System :: OS Independent
Classifier: Programming Language :: Python :: 3
Classifier: Programming Language :: Python :: 3.8
Classifier: Programming Language :: Python :: 3.9
Classifier: Programming Language :: Python :: 3.10
Classifier: Programming Language :: Python :: 3.11
Classifier: Programming Language :: Python :: 3.12
Classifier: Topic :: Internet :: WWW/HTTP
Classifier: Topic :: Scientific/Engineering :: Information Analysis
Classifier: Topic :: Software Development :: Libraries :: Python Modules
Classifier: Topic :: Text Processing :: General
Classifier: Topic :: Utilities
Requires-Python: >=3.8
License-File: LICENSE
Requires-Dist: requests>=2.28.0
Requires-Dist: beautifulsoup4>=4.11.0
Requires-Dist: pydantic>=2.0.0
Requires-Dist: click>=8.0.0
Requires-Dist: openai>=1.0.0
Requires-Dist: python-dotenv>=1.0.0
Requires-Dist: lxml>=4.9.0
Requires-Dist: scikit-learn>=1.3.0
Requires-Dist: oxenai>=0.38.0
Requires-Dist: selenium>=4.15.0
Requires-Dist: webdriver-manager>=4.0.0
Dynamic: author
Dynamic: classifier
Dynamic: description
Dynamic: description-content-type
Dynamic: home-page
Dynamic: keywords
Dynamic: license-file
Dynamic: project-url
Dynamic: requires-dist
Dynamic: requires-python
Dynamic: summary
